ytp2mp3/PlaylistDownloader.py
ytp2mp3/__init__.py
ytp2mp3/cli.py
ytp2mp3-0.2.0.dist-info/licenses/LICENSE
ytp2mp3-0.2.0.dist-info/METADATA
ytp2mp3-0.2.0.dist-info/WHEEL
ytp2mp3-0.2.0.dist-info/entry_points.txt
ytp2mp3-0.2.0.dist-info/top_level.txt
ytp2mp3-0.2.0.dist-info/RECORD
