Metadata-Version: 2.4
Name: ytp2mp3
Version: 0.2.0
Summary: A CLI tool to convert YouTube playlists into a single MP3 file
Author-email: Aaron Zachariah <aaron.zachariah@gmail.com>
License: MIT
Project-URL: Homepage, https://github.com/zachaa2/ytp2mp3
Requires-Python: >=3.7
License-File: LICENSE
Requires-Dist: yt-dlp
Requires-Dist: pydub
Dynamic: license-file
